allegro_pl/__init__.py
allegro_pl/allegro.py
allegro_pl/oauth.py
allegro_pl/rest.py
allegro_pl/soap.py
allegro_pl/utils.py
mattes_allegro_pl-0.9.1.dist-info/WHEEL
mattes_allegro_pl-0.9.1.dist-info/METADATA
mattes_allegro_pl-0.9.1.dist-info/RECORD
