Metadata-Version: 2.1
Name: mattes-allegro-pl
Version: 0.9.1
Summary: Python client for Allegro.pl API
Home-page: https://github.com/mattesilver/allegro-pl/
License: MIT
Author: Raphael Krupinski
Requires-Python: >=3.7,<4.0
Classifier: License :: OSI Approved :: MIT License
Classifier: Programming Language :: Python :: 3
Classifier: Programming Language :: Python :: 3.7
Classifier: Programming Language :: Python :: 3.8
Requires-Dist: allegro-pl-rest-api (>=2020.1,<2021.0)
Requires-Dist: oauthlib (>=3.0,<4.0)
Requires-Dist: requests-oauthlib (>=1.2,<2.0)
Requires-Dist: tenacity (>=6.0.0,<7.0.0)
Requires-Dist: zeep (>=3.3,<4.0)
Project-URL: Repository, https://github.com/mattesilver/allegro-pl/
